datebs/__init__.py
datebs/__main__.py
datebs/datebs.py
datebs-0.0.6.dist-info/METADATA
datebs-0.0.6.dist-info/WHEEL
datebs-0.0.6.dist-info/top_level.txt
datebs-0.0.6.dist-info/RECORD
