Metadata-Version: 2.1
Name: datebs
Version: 0.0.6
Summary: convert date from BS to AD and vice versa
Home-page: https://github.com/shubhajeet/datebspy
Author: Sujit Maharjan
Author-email: shubhajeet.per@gmail.com
License: UNKNOWN
Platform: UNKNOWN
Classifier: Programming Language :: Python :: 3
Classifier: Operating System :: OS Independent
Requires-Python: >=3.6
